mcp_builder/__init__.py
mcp_builder/cli.py
mcp_builder/core.py
mcp_builder/logging.py
mcp_builder/planner.py
mcp_builder/types.py
mcp_builder/validator.py
mcp_builder/buildpacks/__init__.py
mcp_builder/buildpacks/binary.py
mcp_builder/buildpacks/go.py
mcp_builder/buildpacks/node.py
mcp_builder/buildpacks/python.py
mcp_builder/buildpacks/rust.py
mcp_builder/conformance/__init__.py
mcp_builder/conformance/runner.py
mcp_builder/conformance/testspec.py
mcp_builder/detect/__init__.py
mcp_builder/detect/base.py
mcp_builder/detect/node_pkg.py
mcp_builder/detect/python_ast.py
mcp_builder/detect/repo.py
mcp_builder/installer/__init__.py
mcp_builder/installer/env_node.py
mcp_builder/installer/env_python.py
mcp_builder/installer/install copy.py
mcp_builder/installer/install.py
mcp_builder/installer/surfaces.py
mcp_builder/package/__init__.py
mcp_builder/package/docker.py
mcp_builder/package/npm.py
mcp_builder/package/pypi.py
mcp_builder/package/zip.py
mcp_builder/schema/mcp.server.schema.json
mcp_builder/schema/plan.schema.json
mcp_builder/schema/runner.schema.json
mcp_builder/security/__init__.py
mcp_builder/security/archive.py
mcp_builder/signing/__init__.py
mcp_builder/signing/checks.py
mcp_builder/signing/sbom.py
mcp_builder-0.1.0.dist-info/METADATA
mcp_builder-0.1.0.dist-info/WHEEL
mcp_builder-0.1.0.dist-info/entry_points.txt
mcp_builder-0.1.0.dist-info/licenses/LICENSE
mcp_builder-0.1.0.dist-info/RECORD
