Metadata-Version: 2.4
Name: mcp-builder
Version: 0.1.0
Summary: Build, package, install, and validate MCP servers (Matrix Hub–compatible).
Project-URL: Homepage, https://github.com/ruslanmv/mcp-builder
Project-URL: Repository, https://github.com/ruslanmv/mcp-builder
Project-URL: Documentation, https://ruslanmv.github.io/mcp-builder
Author-email: Ruslan Magana Vsevolodovna <contact@ruslanmv.com>
License: Apache-2.0
License-File: LICENSE
Keywords: builder,cli,matrixhub,mcp,modelcontextprotocol
Classifier: Development Status :: 3 - Alpha
Classifier: Environment :: Console
Classifier: Intended Audience :: Developers
Classifier: License :: OSI Approved :: Apache Software License
Classifier: Programming Language :: Python
Classifier: Programming Language :: Python :: 3
Classifier: Programming Language :: Python :: 3.11
Classifier: Programming Language :: Python :: 3.12
Classifier: Topic :: Software Development :: Build Tools
Requires-Python: >=3.11
Requires-Dist: anyio>=4
Requires-Dist: filelock>=3.14
Requires-Dist: httpx>=0.27
Requires-Dist: jinja2>=3.1
Requires-Dist: jsonschema>=4.22
Requires-Dist: pydantic>=2.7
Requires-Dist: rich>=13
Requires-Dist: typer>=0.12
Provides-Extra: dev
Requires-Dist: black>=24.3; extra == 'dev'
Requires-Dist: mypy>=1.10; extra == 'dev'
Requires-Dist: pytest-asyncio>=0.23; extra == 'dev'
Requires-Dist: pytest-timeout>=2.3.1; extra == 'dev'
Requires-Dist: pytest>=8; extra == 'dev'
Requires-Dist: ruff>=0.4; extra == 'dev'
Provides-Extra: docs
Requires-Dist: mkdocs-material>=9.5; extra == 'docs'
Requires-Dist: mkdocs>=1.6; extra == 'docs'
